json_modify.py
json_modify-1.0.1.dist-info/LICENSE
json_modify-1.0.1.dist-info/METADATA
json_modify-1.0.1.dist-info/WHEEL
json_modify-1.0.1.dist-info/top_level.txt
json_modify-1.0.1.dist-info/RECORD
