Metadata-Version: 2.1
Name: json-modify
Version: 1.0.1
Summary: Simple to use json/yaml modifier
Home-page: UNKNOWN
Author: Oleksii Petrenko
Author-email: oleksiiypetrenko@gmail.com
License: MIT
Project-URL: Website, https://github.com/Enacero/json_modify
Project-URL: PyPi, https://pypi.python.org/pypi/json_modify
Keywords: json yaml
Platform: UNKNOWN
Classifier: Intended Audience :: Developers
Classifier: License :: OSI Approved :: MIT License
Classifier: Programming Language :: Python :: 3 :: Only
Classifier: Programming Language :: Python :: 3.5
Classifier: Programming Language :: Python :: 3.6
Classifier: Programming Language :: Python :: 3.7
Classifier: Programming Language :: Python :: 3.8
Requires-Python: >3.5
Requires-Dist: PyYAML (>=5.3.1)
